stellata/__init__.py
stellata/database.py
stellata/field.py
stellata/fields.py
stellata/index.py
stellata/model.py
stellata/query.py
stellata/relation.py
stellata/relations.py
stellata/schema.py
stellata/tests/__init__.py
stellata/tests/base.py
stellata/tests/test_database.py
stellata/tests/test_model.py
stellata/tests/test_query.py
stellata/tests/test_schema.py
stellata-0.0.2.dist-info/DESCRIPTION.rst
stellata-0.0.2.dist-info/METADATA
stellata-0.0.2.dist-info/RECORD
stellata-0.0.2.dist-info/WHEEL
stellata-0.0.2.dist-info/metadata.json
stellata-0.0.2.dist-info/top_level.txt
