Metadata-Version: 2.0
Name: stellata
Version: 0.0.2
Summary: A simple ORM for PostgreSQL.
Home-page: https://github.com/tmacwill/stellata
Author: Tommy MacWilliam
Author-email: tmacwilliam@cs.harvard.edu
License: MIT
Keywords: orm postgres postgresql
Platform: UNKNOWN
Classifier: Development Status :: 4 - Beta
Classifier: License :: OSI Approved :: MIT License
Classifier: Intended Audience :: Developers
Classifier: Programming Language :: Python :: 3 :: Only
Classifier: Topic :: Database
Requires-Dist: psycopg2
